{
    "schools": [
        {
            "universal-id": "1710244",
            "nces-id": null,
            "state-id": null,
            "name": "Gateway Legacy Christian Academy",
            "school-summary": "Gateway Legacy Christian Academy, a private school located in Glen Carbon, IL, serves grades PK-12 in the .",
            "type": "private",
            "level-codes": "p,e,m,h",
            "level": "PK,KG,1,2,3,4,5,6,7,8,9,10,11,12",
            "street": "97 Oaklawn Rd. ",
            "city": "Glen Carbon",
            "state": "IL",
            "fipscounty": 17119,
            "zip": "62034",
            "phone": "(618) 288-0452",
            "fax": "(618) 288-0453",
            "county": "Madison",
            "lat": 38.759617,
            "lon": -89.947906,
            "district-name": null,
            "district-id": 0,
            "web-site": "http://gatewayfamilychurch.com",
            "overview-url": "https://www.greatschools.org/illinois/glen-carbon/10244-Gateway-Legacy-Christian-Academy/",
            "rating": null,
            "year": null,
            "rating-description": "The GreatSchools Rating helps parents compare schools within a state based on a variety of school quality indicators and provides a helpful picture of how effectively each school serves all of its students. Ratings are on a scale of 1 (below average) to 10 (above average) and can include test scores, college readiness, academic progress, advanced courses, equity, discipline and attendance data. We also advise parents to visit schools, consider other information on school performance and programs, and consider family needs as part of the school selection process."
        },
        {
            "universal-id": "1710547",
            "nces-id": null,
            "state-id": "41057099X0000",
            "name": "Gateway Legacy Christian Academy",
            "school-summary": "Gateway Legacy Christian Academy, a private school located in Glen Carbon, IL, serves grades PK-12 in the .",
            "type": "private",
            "level-codes": "p,e,m,h",
            "level": "PK,KG,1,2,3,4,5,6,7,8,9,10,11,12",
            "street": "97 Oaklawn Drive",
            "city": "Glen Carbon",
            "state": "IL",
            "fipscounty": 17119,
            "zip": "62034",
            "phone": "(618) 288-0452",
            "fax": "(618) 288-0453",
            "county": "Madison",
            "lat": 38.75919,
            "lon": -89.944656,
            "district-name": null,
            "district-id": 0,
            "web-site": "http://gatewayfamilychurch.com/391684.ihtml",
            "overview-url": "https://www.greatschools.org/illinois/glen-carbon/10547-Gateway-Legacy-Christian-Academy/",
            "rating": null,
            "year": null,
            "rating-description": "The GreatSchools Rating helps parents compare schools within a state based on a variety of school quality indicators and provides a helpful picture of how effectively each school serves all of its students. Ratings are on a scale of 1 (below average) to 10 (above average) and can include test scores, college readiness, academic progress, advanced courses, equity, discipline and attendance data. We also advise parents to visit schools, consider other information on school performance and programs, and consider family needs as part of the school selection process."
        },
        {
            "universal-id": "1701908",
            "nces-id": "171353001641",
            "state-id": "4105700702006",
            "name": "Glen Carbon Elementary School",
            "school-summary": "Glen Carbon Elementary School, a public school located in Glen Carbon, IL, serves grades PK-2 in the Edwardsville Community Unit School District 7.",
            "type": "public",
            "level-codes": "p,e",
            "level": "PK,KG,1,2",
            "street": "141 Birger Avenue",
            "city": "Glen Carbon",
            "state": "IL",
            "fipscounty": 17119,
            "zip": "62034",
            "phone": "(618) 692-7460",
            "fax": null,
            "county": "Madison County",
            "lat": 38.749992,
            "lon": -89.976906,
            "district-name": "Edwardsville Community Unit School District 7",
            "district-id": 426,
            "web-site": "http://www.ecusd7.org/gc/",
            "overview-url": "https://www.greatschools.org/illinois/glen-carbon/1908-Glen-Carbon-Elementary-School/",
            "rating": null,
            "year": null,
            "rating-description": "The GreatSchools Rating helps parents compare schools within a state based on a variety of school quality indicators and provides a helpful picture of how effectively each school serves all of its students. Ratings are on a scale of 1 (below average) to 10 (above average) and can include test scores, college readiness, academic progress, advanced courses, equity, discipline and attendance data. We also advise parents to visit schools, consider other information on school performance and programs, and consider family needs as part of the school selection process."
        },
        {
            "universal-id": "1705277",
            "nces-id": "A9102448",
            "state-id": "41057089Z0000",
            "name": "Lahr-Well Academy",
            "school-summary": "Lahr-Well Academy, a private school located in Glen Carbon, IL, serves grades Ungraded in the .",
            "type": "private",
            "level-codes": "e,m,h",
            "level": "UG",
            "street": "PO BOX",
            "city": "Glen Carbon",
            "state": "IL",
            "fipscounty": 17119,
            "zip": "62034",
            "phone": "(618) 288-8034",
            "fax": null,
            "county": "MADISON",
            "lat": 38.762985,
            "lon": -89.958015,
            "district-name": null,
            "district-id": 0,
            "web-site": null,
            "overview-url": "https://www.greatschools.org/illinois/glen-carbon/5277-Lahr-Well-Academy/",
            "rating": null,
            "year": null,
            "rating-description": "The GreatSchools Rating helps parents compare schools within a state based on a variety of school quality indicators and provides a helpful picture of how effectively each school serves all of its students. Ratings are on a scale of 1 (below average) to 10 (above average) and can include test scores, college readiness, academic progress, advanced courses, equity, discipline and attendance data. We also advise parents to visit schools, consider other information on school performance and programs, and consider family needs as part of the school selection process."
        },
        {
            "universal-id": "1707308",
            "nces-id": null,
            "state-id": "41057001Z0000",
            "name": "Faith Baptist Academy",
            "school-summary": "Faith Baptist Academy, a private school located in Glen Carbon, IL, serves grades Ungraded in the .",
            "type": "private",
            "level-codes": "e,m,h",
            "level": "UG",
            "street": "Rr 139 3899",
            "city": "Glen Carbon",
            "state": "IL",
            "fipscounty": 17119,
            "zip": "62034",
            "phone": "(618) 285-6411",
            "fax": null,
            "county": "Madison",
            "lat": 38.753063,
            "lon": -89.998146,
            "district-name": null,
            "district-id": 0,
            "web-site": null,
            "overview-url": "https://www.greatschools.org/illinois/glen-carbon/7308-Faith-Baptist-Academy/",
            "rating": null,
            "year": null,
            "rating-description": "The GreatSchools Rating helps parents compare schools within a state based on a variety of school quality indicators and provides a helpful picture of how effectively each school serves all of its students. Ratings are on a scale of 1 (below average) to 10 (above average) and can include test scores, college readiness, academic progress, advanced courses, equity, discipline and attendance data. We also advise parents to visit schools, consider other information on school performance and programs, and consider family needs as part of the school selection process."
        },
        {
            "universal-id": "1708546",
            "nces-id": null,
            "state-id": null,
            "name": "La Petite Academy #2901",
            "school-summary": "La Petite Academy #2901, a private school located in Glen Carbon, IL, serves grades PK-K in the .",
            "type": "private",
            "level-codes": "p,e",
            "level": "PK,KG",
            "street": "2 Auerbach Place",
            "city": "Glen Carbon",
            "state": "IL",
            "fipscounty": 17119,
            "zip": "62034",
            "phone": "(618) 288-3486",
            "fax": null,
            "county": "Madison",
            "lat": 38.775154,
            "lon": -89.991837,
            "district-name": null,
            "district-id": 0,
            "web-site": "https://www.lapetite.com/your-local-school/glen-carbon-il-7100/",
            "overview-url": "https://www.greatschools.org/illinois/glen-carbon/8546-La-Petite-Academy-2901/",
            "rating": null,
            "year": null,
            "rating-description": "The GreatSchools Rating helps parents compare schools within a state based on a variety of school quality indicators and provides a helpful picture of how effectively each school serves all of its students. Ratings are on a scale of 1 (below average) to 10 (above average) and can include test scores, college readiness, academic progress, advanced courses, equity, discipline and attendance data. We also advise parents to visit schools, consider other information on school performance and programs, and consider family needs as part of the school selection process."
        },
        {
            "universal-id": "1709827",
            "nces-id": "171353006020",
            "state-id": "4105700702012",
            "name": "Albert Cassens Elementary School",
            "school-summary": "Albert Cassens Elementary School, a public school located in Glen Carbon, IL, serves grades 3-5 in the Edwardsville Community Unit School District 7.It has received a GreatSchools Rating of 5 out of 10, based on a variety of school quality measures.",
            "type": "public",
            "level-codes": "e",
            "level": "3,4,5",
            "street": "1014 Glen Crossing Road",
            "city": "Glen Carbon",
            "state": "IL",
            "fipscounty": 17119,
            "zip": "62034",
            "phone": "(618) 655-6150",
            "fax": null,
            "county": "Madison County",
            "lat": 38.751518,
            "lon": -89.93589,
            "district-name": "Edwardsville Community Unit School District 7",
            "district-id": 426,
            "web-site": null,
            "overview-url": "https://www.greatschools.org/illinois/glen-carbon/9827-Albert-Cassens-Elementary-School/",
            "rating": "5",
            "year": 2023,
            "rating-description": "The GreatSchools Rating helps parents compare schools within a state based on a variety of school quality indicators and provides a helpful picture of how effectively each school serves all of its students. Ratings are on a scale of 1 (below average) to 10 (above average) and can include test scores, college readiness, academic progress, advanced courses, equity, discipline and attendance data. We also advise parents to visit schools, consider other information on school performance and programs, and consider family needs as part of the school selection process."
        }
    ],
    "cur_page": 0,
    "items_per_page": 50,
    "max_page_num": 0,
    "total_count": 7,
    "links": {
        "self": "/schools?city=Glen+Carbon&limit=50&state=IL&page=0",
        "prev": "",
        "next": "",
        "first": "/schools?city=Glen+Carbon&limit=50&state=IL&page=0",
        "last": "/schools?city=Glen+Carbon&limit=50&state=IL&page=0"
    }
}