{
    "schools": [
        {
            "universal-id": "1703268",
            "nces-id": "173087003219",
            "state-id": "1305810000002",
            "name": "Patoka Sr High School",
            "school-summary": "Patoka Sr High School, a public school located in Patoka, IL, serves grades 9-12 in the Patoka Community Unit School District 100.It has received a GreatSchools Rating of 2 out of 10, based on a variety of school quality measures.",
            "type": "public",
            "level-codes": "h",
            "level": "9,10,11,12",
            "street": "1220 Kinoka Road",
            "city": "Patoka",
            "state": "IL",
            "fipscounty": 17121,
            "zip": "62875",
            "phone": "(618) 432-5440",
            "fax": null,
            "county": "Marion County",
            "lat": 38.764297,
            "lon": -89.085281,
            "district-name": "Patoka Community Unit School District 100",
            "district-id": 807,
            "web-site": "http://www.patokaschool.com",
            "overview-url": "https://www.greatschools.org/illinois/patoka/3268-Patoka-Sr-High-School/",
            "rating": "2",
            "year": 2023,
            "rating-description": "The GreatSchools Rating helps parents compare schools within a state based on a variety of school quality indicators and provides a helpful picture of how effectively each school serves all of its students. Ratings are on a scale of 1 (below average) to 10 (above average) and can include test scores, college readiness, academic progress, advanced courses, equity, discipline and attendance data. We also advise parents to visit schools, consider other information on school performance and programs, and consider family needs as part of the school selection process."
        },
        {
            "universal-id": "1703269",
            "nces-id": "173087004787",
            "state-id": "1305810002001",
            "name": "Patoka Elementary School",
            "school-summary": "Patoka Elementary School, a public school located in Patoka, IL, serves grades PK-6 in the Patoka Community Unit School District 100.It has received a GreatSchools Rating of 6 out of 10, based on a variety of school quality measures.",
            "type": "public",
            "level-codes": "p,e",
            "level": "PK,KG,1,2,3,4,5,6",
            "street": "1220 Kinoka Road",
            "city": "Patoka",
            "state": "IL",
            "fipscounty": 17121,
            "zip": "62875",
            "phone": "(618) 432-5200",
            "fax": null,
            "county": "Marion County",
            "lat": 38.764297,
            "lon": -89.085281,
            "district-name": "Patoka Community Unit School District 100",
            "district-id": 807,
            "web-site": "http://www.patokaschool.com",
            "overview-url": "https://www.greatschools.org/illinois/patoka/3269-Patoka-Elementary-School/",
            "rating": "6",
            "year": 2023,
            "rating-description": "The GreatSchools Rating helps parents compare schools within a state based on a variety of school quality indicators and provides a helpful picture of how effectively each school serves all of its students. Ratings are on a scale of 1 (below average) to 10 (above average) and can include test scores, college readiness, academic progress, advanced courses, equity, discipline and attendance data. We also advise parents to visit schools, consider other information on school performance and programs, and consider family needs as part of the school selection process."
        },
        {
            "universal-id": "1703270",
            "nces-id": "173087004788",
            "state-id": "1305810001001",
            "name": "Patoka Jr High School",
            "school-summary": "Patoka Jr High School, a public school located in Patoka, IL, serves grades 7-8 in the Patoka Community Unit School District 100.It has received a GreatSchools Rating of 5 out of 10, based on a variety of school quality measures.",
            "type": "public",
            "level-codes": "m",
            "level": "7,8",
            "street": "1220 Kinoka Road",
            "city": "Patoka",
            "state": "IL",
            "fipscounty": 17121,
            "zip": "62875",
            "phone": "(618) 432-5200",
            "fax": null,
            "county": "Marion County",
            "lat": 38.764297,
            "lon": -89.085281,
            "district-name": "Patoka Community Unit School District 100",
            "district-id": 807,
            "web-site": "http://www.patokaschool.com",
            "overview-url": "https://www.greatschools.org/illinois/patoka/3270-Patoka-Jr-High-School/",
            "rating": "5",
            "year": 2023,
            "rating-description": "The GreatSchools Rating helps parents compare schools within a state based on a variety of school quality indicators and provides a helpful picture of how effectively each school serves all of its students. Ratings are on a scale of 1 (below average) to 10 (above average) and can include test scores, college readiness, academic progress, advanced courses, equity, discipline and attendance data. We also advise parents to visit schools, consider other information on school performance and programs, and consider family needs as part of the school selection process."
        }
    ],
    "cur_page": 0,
    "items_per_page": 50,
    "max_page_num": 0,
    "total_count": 3,
    "links": {
        "self": "/schools?city=Patoka&limit=50&state=IL&page=0",
        "prev": "",
        "next": "",
        "first": "/schools?city=Patoka&limit=50&state=IL&page=0",
        "last": "/schools?city=Patoka&limit=50&state=IL&page=0"
    }
}