{
    "schools": [
        {
            "universal-id": "1707544",
            "nces-id": "A0501614",
            "state-id": "21028001Z0000",
            "name": "Thompsonville Christian School",
            "school-summary": "Thompsonville Christian School, a private school located in Thompsonville, IL, serves grades K-8 in the .",
            "type": "private",
            "level-codes": "e,m",
            "level": "KG,1,2,3,4,5,6,7,8",
            "street": "PO BOX 53",
            "city": "Thompsonville",
            "state": "IL",
            "fipscounty": 17055,
            "zip": "62890",
            "phone": "(618) 627-2065",
            "fax": null,
            "county": "FRANKLIN",
            "lat": 37.908051,
            "lon": -88.730156,
            "district-name": null,
            "district-id": 0,
            "web-site": null,
            "overview-url": "https://www.greatschools.org/illinois/thompsonville/7544-Thompsonville-Christian-School/",
            "rating": null,
            "year": null,
            "rating-description": "The GreatSchools Rating helps parents compare schools within a state based on a variety of school quality indicators and provides a helpful picture of how effectively each school serves all of its students. Ratings are on a scale of 1 (below average) to 10 (above average) and can include test scores, college readiness, academic progress, advanced courses, equity, discipline and attendance data. We also advise parents to visit schools, consider other information on school performance and programs, and consider family needs as part of the school selection process."
        },
        {
            "universal-id": "1709793",
            "nces-id": "170138205940",
            "state-id": "2102817400001",
            "name": "Thompsonville High School",
            "school-summary": "Thompsonville High School, a public school located in Thompsonville, IL, serves grades 9-12 in the Thompsonville Community Unit School District 174.It has received a GreatSchools Rating of 5 out of 10, based on a variety of school quality measures.",
            "type": "public",
            "level-codes": "h",
            "level": "9,10,11,12",
            "street": "21191 Shawneetown Road",
            "city": "Thompsonville",
            "state": "IL",
            "fipscounty": 17055,
            "zip": "62890",
            "phone": "(618) 627-2446",
            "fax": null,
            "county": "Franklin County",
            "lat": 37.919525,
            "lon": -88.765785,
            "district-name": "Thompsonville Community Unit School District 174",
            "district-id": 1357,
            "web-site": "http://www.tvilleschools.org",
            "overview-url": "https://www.greatschools.org/illinois/thompsonville/9793-Thompsonville-High-School/",
            "rating": "5",
            "year": 2023,
            "rating-description": "The GreatSchools Rating helps parents compare schools within a state based on a variety of school quality indicators and provides a helpful picture of how effectively each school serves all of its students. Ratings are on a scale of 1 (below average) to 10 (above average) and can include test scores, college readiness, academic progress, advanced courses, equity, discipline and attendance data. We also advise parents to visit schools, consider other information on school performance and programs, and consider family needs as part of the school selection process."
        },
        {
            "universal-id": "1709794",
            "nces-id": "170138205923",
            "state-id": "2102817402001",
            "name": "Thompsonville Grade  School",
            "school-summary": "Thompsonville Grade  School, a public school located in Thompsonville, IL, serves grades PK-8 in the Thompsonville Community Unit School District 174.It has received a GreatSchools Rating of 4 out of 10, based on a variety of school quality measures.",
            "type": "public",
            "level-codes": "p,e,m",
            "level": "PK,KG,1,2,3,4,5,6,7,8",
            "street": "21191 Shawneetown Road",
            "city": "Thompsonville",
            "state": "IL",
            "fipscounty": 17055,
            "zip": "62890",
            "phone": "(618) 627-2446",
            "fax": null,
            "county": "Franklin County",
            "lat": 37.919525,
            "lon": -88.765785,
            "district-name": "Thompsonville Community Unit School District 174",
            "district-id": 1357,
            "web-site": "http://www.tvilleschools.org",
            "overview-url": "https://www.greatschools.org/illinois/thompsonville/9794-Thompsonville-Grade--School/",
            "rating": "4",
            "year": 2023,
            "rating-description": "The GreatSchools Rating helps parents compare schools within a state based on a variety of school quality indicators and provides a helpful picture of how effectively each school serves all of its students. Ratings are on a scale of 1 (below average) to 10 (above average) and can include test scores, college readiness, academic progress, advanced courses, equity, discipline and attendance data. We also advise parents to visit schools, consider other information on school performance and programs, and consider family needs as part of the school selection process."
        }
    ],
    "cur_page": 0,
    "items_per_page": 50,
    "max_page_num": 0,
    "total_count": 3,
    "links": {
        "self": "/schools?city=Thompsonville&limit=50&state=IL&page=0",
        "prev": "",
        "next": "",
        "first": "/schools?city=Thompsonville&limit=50&state=IL&page=0",
        "last": "/schools?city=Thompsonville&limit=50&state=IL&page=0"
    }
}